deckfs-0.1.2.dist-info/licenses/LICENSE
src/__init__.py
src/__main__.py
src/cli.py
src/config.yaml.example
src/runner.py
src/setup.py
src/core/__init__.py
src/core/button.py
src/core/coordinator.py
src/core/daemon.py
src/core/files.py
src/core/hardware.py
src/core/processes.py
src/utils/__init__.py
src/utils/config.py
src/utils/debouncer.py
src/utils/file_utils.py
src/utils/image_utils.py
src/utils/logger.py
deckfs-0.1.2.dist-info/METADATA
deckfs-0.1.2.dist-info/WHEEL
deckfs-0.1.2.dist-info/entry_points.txt
deckfs-0.1.2.dist-info/top_level.txt
deckfs-0.1.2.dist-info/RECORD
