Metadata-Version: 2.4
Name: deckfs
Version: 0.1.2
Summary: Linux daemon for Stream Deck control without GUI through filesystem
Author-email: Denis Gryzlov <gryzlov@gmail.com>
License: MIT
Project-URL: Homepage, https://github.com/spinogrizz/deckfs
Project-URL: Bug Reports, https://github.com/spinogrizz/deckfs/issues
Project-URL: Source, https://github.com/spinogrizz/deckfs
Project-URL: Repository, https://github.com/spinogrizz/deckfs
Project-URL: Documentation, https://github.com/spinogrizz/deckfs#readme
Keywords: stream-deck,linux,daemon,filesystem
Classifier: Development Status :: 3 - Alpha
Classifier: Intended Audience :: End Users/Desktop
Classifier: Operating System :: POSIX :: Linux
Classifier: Programming Language :: Python :: 3
Classifier: Programming Language :: Python :: 3.8
Classifier: Programming Language :: Python :: 3.9
Classifier: Programming Language :: Python :: 3.10
Classifier: Programming Language :: Python :: 3.11
Classifier: Programming Language :: Python :: 3.12
Classifier: Topic :: System :: Hardware
Classifier: Topic :: Utilities
Requires-Python: >=3.8
License-File: LICENSE
Requires-Dist: streamdeck>=0.9.0
Requires-Dist: Pillow>=10.0.0
Requires-Dist: watchdog>=3.0.0
Requires-Dist: PyYAML>=6.0
Requires-Dist: pyudev>=0.24.0
Requires-Dist: setproctitle>=1.3.0
Provides-Extra: dev
Requires-Dist: pytest>=7.0.0; extra == "dev"
Requires-Dist: pytest-cov>=4.0.0; extra == "dev"
Requires-Dist: pytest-mock>=3.10.0; extra == "dev"
Dynamic: license-file
